spectrasketch/__init__.py
spectrasketch/core.py
spectrasketch-0.1.3.dist-info/licenses/LICENSE.txt
spectrasketch-0.1.3.dist-info/METADATA
spectrasketch-0.1.3.dist-info/WHEEL
spectrasketch-0.1.3.dist-info/top_level.txt
spectrasketch-0.1.3.dist-info/RECORD
