Metadata-Version: 2.4
Name: spectrasketch
Version: 0.1.3
Summary: A Python drawing library for custom shapes, rotation, and interactive editing using OpenCV.
Author: Swathi Baskar
Author-email: Swathi Baskar <swathiibaskarr@gmail.com>
License: 
Requires-Python: >=3.6
License-File: LICENSE.txt
Requires-Dist: numpy
Requires-Dist: opencv-python
Dynamic: author
Dynamic: license-file
Dynamic: requires-python
